jadlog/__init__.py
jadlog/calcula.py
jadlog/pedido.py
jadlog-0.1.0.dist-info/LICENSE
jadlog-0.1.0.dist-info/METADATA
jadlog-0.1.0.dist-info/WHEEL
jadlog-0.1.0.dist-info/top_level.txt
jadlog-0.1.0.dist-info/RECORD
