Metadata-Version: 2.1
Name: jadlog
Version: 0.1.0
Summary: Projeto simples para calculo de frete, cubagem e peso real para transportadora Jadlog 
Home-page: https://github.com/tiagocordeiro/jadlog
Author: Tiago Cordeiro
Author-email: tiago@mulhergorila.com
License: MIT
Platform: UNKNOWN
Classifier: Development Status :: 4 - Beta
Classifier: Environment :: Console
Classifier: Intended Audience :: Developers
Classifier: License :: OSI Approved :: MIT License
Classifier: Natural Language :: Portuguese (Brazilian)
Classifier: Operating System :: OS Independent
Classifier: Programming Language :: Python
Classifier: Programming Language :: Python :: 3
Classifier: Framework :: Paste
Requires-Dist: beautifulsoup4 (>=4.8.2)
Requires-Dist: dynaconf (>=2.2.2)
Requires-Dist: requests (>=2.23.0)
